datacube_alchemist/__init__.py
datacube_alchemist/_dask.py
datacube_alchemist/_utils.py
datacube_alchemist/_version.py
datacube_alchemist/cli.py
datacube_alchemist/settings.py
datacube_alchemist/transforms.py
datacube_alchemist/worker.py
datacube_alchemist-0.6.7.dist-info/LICENSE
datacube_alchemist-0.6.7.dist-info/METADATA
datacube_alchemist-0.6.7.dist-info/WHEEL
datacube_alchemist-0.6.7.dist-info/entry_points.txt
datacube_alchemist-0.6.7.dist-info/top_level.txt
datacube_alchemist-0.6.7.dist-info/zip-safe
datacube_alchemist-0.6.7.dist-info/RECORD
