Metadata-Version: 2.1
Name: datacube-alchemist
Version: 0.6.7
Summary: Batch process Open Data Cube datasets
Home-page: https://github.com/opendatacube/datacube-alchemist
License: Apache License 2.0
Keywords: datacube-alchemist,opendatacube
Platform: any
Classifier: Development Status :: 5 - Production/Stable
Classifier: License :: OSI Approved :: Apache Software License
Classifier: Programming Language :: Python
Classifier: Programming Language :: Python :: 3.6
Classifier: Programming Language :: Python :: 3.7
Classifier: Programming Language :: Python :: 3.8
Classifier: Operating System :: OS Independent
License-File: LICENSE
Requires-Dist: datacube
Requires-Dist: eodatasets3 >=0.22.0
Requires-Dist: attrs >=18.1
Requires-Dist: structlog
Requires-Dist: dask
Requires-Dist: distributed
Requires-Dist: fsspec
Requires-Dist: jsonschema
Requires-Dist: requests
Requires-Dist: odc-algo
Requires-Dist: odc-apps-dc-tools
Requires-Dist: boto3
Requires-Dist: awscli
Requires-Dist: xarray
Requires-Dist: cattrs ==1.0.0 ; python_version < "3.7"
Provides-Extra: dev
Requires-Dist: black ; extra == 'dev'
Requires-Dist: pytest ; extra == 'dev'
Requires-Dist: pytest-cov ; extra == 'dev'
Requires-Dist: moto ; extra == 'dev'
